ignr/__init__.py
ignr/__main__.py
ignr/cli.py
ignr/gitignoreio_api.py
ignr-2.2.dist-info/LICENSE
ignr-2.2.dist-info/METADATA
ignr-2.2.dist-info/WHEEL
ignr-2.2.dist-info/entry_points.txt
ignr-2.2.dist-info/top_level.txt
ignr-2.2.dist-info/RECORD
